workstation_shell/__init__.py
workstation_shell/workstation_shell.py
workstation_shell-0.0.2.dist-info/METADATA
workstation_shell-0.0.2.dist-info/WHEEL
workstation_shell-0.0.2.dist-info/entry_points.txt
workstation_shell-0.0.2.dist-info/top_level.txt
workstation_shell-0.0.2.dist-info/RECORD
